[
  {
    "id": "amazon-soporte-movil-bici-1",
    "title": "Lamicall Soporte Móvil Bicicleta",
    "category": "Accesorios",
    "price": 19.99,
    "old_price": 25.99,
    "url": "https://www.amazon.es/dp/B09MT4N4HW?tag=chollobici0a-21",
    "image": "https://m.media-amazon.com/images/I/71aZYadd%2BYL._AC_SY300_SX300_QL70_ML2_.jpg",
    "source": "amazon",
    "last_checked": "2026-04-25",
    "editor_pick": true,
    "asin": "B09MT4N4HW",
    "brand": "",
    "category_hint": "Accesorios",
    "discount_pct": 23,
    "source_label": "Amazon",
    "recomendacion": 78
  },
  {
    "id": "https://www.decathlon.es/es/p/rueda-bicicleta-sin-pedales-runride-10-pulgadas-trasera-negro-taco/201671/c344m8566233",
    "title": "Rueda Bicicleta Sin Pedales Runride 10\" Pulgadas Trasera Negro Taco",
    "brand": "Decathlon",
    "category": "ciclismo",
    "category_hint": "Travesía todoterreno|ciclismo infantil",
    "image": "https://contents.mediadecathlon.com/p1715991/k$13e473b24ac1609094a1f9aeec6fa589/picture.jpg?f=300x300",
    "url": "https://www.decathlon.es/es/p/rueda-bicicleta-sin-pedales-runride-10-pulgadas-trasera-negro-taco/201671/c344m8566233",
    "affiliate_url": "https://afiliacion.decathlon.es/tracking/clk?fid=107&pca=8566233|Rueda Bicicleta Sin Pedales Runride 10\" Pulgadas Trasera Negro Taco|&act=21712&gel=0&pub=42111&org=2615&url=https://www.decathlon.es/es/p/rueda-bicicleta-sin-pedales-runride-10-pulgadas-trasera-negro-taco/201671/c344m8566233",
    "source": "decathlon",
    "source_label": "Decathlon",
    "price": 11.99,
    "old_price": "",
    "discount_pct": 0,
    "recomendacion": 53,
    "detail_enabled": false,
    "sku": "8566233"
  },
  {
    "id": "1005012049051638",
    "title": ". [LA] Juego de 2 piezas de tacos de liberación rápida para pedales de bicicleta, tacos para zapatillas de ciclismo, piezas de bicicleta para ciclismo.",
    "url": "https://s.click.aliexpress.com/e/_c4a5AMv9",
    "affiliate_url": "https://s.click.aliexpress.com/e/_c4a5AMv9",
    "product_detail_url": "https://es.aliexpress.com/item/1005012049051638.html",
    "image": "https://ae-pic-a1.aliexpress-media.com/kf/Sc81b7e1036224b5f94edd09b425992234.jpg",
    "price": 1.81,
    "old_price": 7.86,
    "currency": "EUR",
    "discount": "77%",
    "source": "aliexpress",
    "source_label": "AliExpress",
    "category": "Componentes",
    "shop_name": "Shop1105317702 Store",
    "rating": "",
    "sales": 0,
    "commission_rate": "7.0%",
    "brand": "",
    "category_hint": "Componentes",
    "discount_pct": 77,
    "recomendacion": 128
  },
  {
    "id": "amazon-portabidon-carbono-1",
    "title": "ESEN-SP Portabidón Carbono Ultralight",
    "category": "Accesorios",
    "price": 14.99,
    "old_price": 19.99,
    "url": "https://www.amazon.es/dp/B07QVC1B7C?tag=chollobici0a-21",
    "image": "/assets/placeholder-product.svg",
    "source": "amazon",
    "last_checked": "2026-04-25",
    "editor_pick": false,
    "asin": "B07QVC1B7C",
    "brand": "",
    "category_hint": "Accesorios",
    "discount_pct": 25,
    "source_label": "Amazon",
    "recomendacion": 68
  },
  {
    "id": "https://www.decathlon.es/es/p/cuerpo-casete-mtb-9-10-velocidades-d952-tse-boost-rodamientos-cono-cazoleta/341109/m8758041",
    "title": "Cuerpo Casete MTB 9/10 Velocidades D952 TSE Boost Rodamientos Cono Cazoleta",
    "brand": "Decathlon",
    "category": "ciclismo",
    "category_hint": "Btt travesía",
    "image": "https://contents.mediadecathlon.com/p2513564/k$b13c366ba12c3cf94fd2c2b58f76f9df/picture.jpg?f=300x300",
    "url": "https://www.decathlon.es/es/p/cuerpo-casete-mtb-9-10-velocidades-d952-tse-boost-rodamientos-cono-cazoleta/341109/m8758041",
    "affiliate_url": "https://afiliacion.decathlon.es/tracking/clk?fid=107&pca=8758041|Cuerpo Casete MTB 9/10 Velocidades D952 TSE Boost Rodamientos Cono Cazoleta|&act=21712&gel=0&pub=42111&org=2615&url=https://www.decathlon.es/es/p/cuerpo-casete-mtb-9-10-velocidades-d952-tse-boost-rodamientos-cono-cazoleta/341109/m8758041",
    "source": "decathlon",
    "source_label": "Decathlon",
    "price": 14.99,
    "old_price": "",
    "discount_pct": 0,
    "recomendacion": 53,
    "detail_enabled": false,
    "sku": "8758041"
  },
  {
    "id": "1005005036664896",
    "title": "Soporte Universal para teléfono móvil para Xiaomi M365 pro Ninebot, soporte de montaje en manillar para patinete eléctrico, soporte para teléfono móvil para bicicleta",
    "url": "https://s.click.aliexpress.com/e/_c2JKgfGJ",
    "affiliate_url": "https://s.click.aliexpress.com/e/_c2JKgfGJ",
    "product_detail_url": "https://es.aliexpress.com/item/1005005036664896.html",
    "image": "https://ae-pic-a1.aliexpress-media.com/kf/S4f01bd4a705f485c9b1bd1d8411c80d9j.jpg",
    "price": 3.29,
    "old_price": 9.88,
    "currency": "EUR",
    "discount": "66%",
    "source": "aliexpress",
    "source_label": "AliExpress",
    "category": "Accesorios",
    "shop_name": "DUBULL Official Store",
    "rating": "85.7%",
    "sales": 173,
    "commission_rate": "7.0%",
    "brand": "",
    "category_hint": "Accesorios",
    "discount_pct": 66,
    "recomendacion": 128
  },
  {
    "id": "amazon-inflador-electrico-1",
    "title": "GPUTEK Inflador Eléctrico Bicicleta",
    "category": "Herramientas",
    "price": 39.99,
    "old_price": 49.99,
    "url": "https://www.amazon.es/dp/B0D8HPJGQX?tag=chollobici0a-21",
    "image": "https://m.media-amazon.com/images/I/61005AmP8tL._AC_SY300_SX300_QL70_ML2_.jpg",
    "source": "amazon",
    "last_checked": "2026-04-25",
    "editor_pick": false,
    "asin": "B0D8HPJGQX",
    "brand": "",
    "category_hint": "Herramientas",
    "discount_pct": 20,
    "source_label": "Amazon",
    "recomendacion": 66
  },
  {
    "id": "https://www.decathlon.es/es/p/culotte-interior-ciclismo-mtb-100-hombre-negro/357210/c382c382m8902443",
    "title": "Culotte Interior Ciclismo MTB 100 Hombre Negro",
    "brand": "Decathlon",
    "category": "ciclismo",
    "category_hint": "Travesía todoterreno|Viaje todocamino|Btt travesía|Gravel",
    "image": "https://contents.mediadecathlon.com/p3103000/k$a73746fd82629b4955329e2d6e8cd642/picture.jpg?f=300x300",
    "url": "https://www.decathlon.es/es/p/culotte-interior-ciclismo-mtb-100-hombre-negro/357210/c382c382m8902443",
    "affiliate_url": "https://afiliacion.decathlon.es/tracking/clk?fid=107&pca=8902443|Culotte Interior Ciclismo MTB 100 Hombre Negro|&act=21712&gel=0&pub=42111&org=2615&url=https://www.decathlon.es/es/p/culotte-interior-ciclismo-mtb-100-hombre-negro/357210/c382c382m8902443",
    "source": "decathlon",
    "source_label": "Decathlon",
    "price": 14.99,
    "old_price": "",
    "discount_pct": 0,
    "recomendacion": 53,
    "detail_enabled": false,
    "sku": "8902443"
  },
  {
    "id": "1005006021054387",
    "title": "HUALONG Jaula para botella de agua de bicicleta de fibra de carbono 3K Jaulas para soporte de botella de agua para bicicleta de grava MTB de carretera, negro mate, peso (16 ± 2 g)",
    "url": "https://s.click.aliexpress.com/e/_c36ptVsP",
    "affiliate_url": "https://s.click.aliexpress.com/e/_c36ptVsP",
    "product_detail_url": "https://es.aliexpress.com/item/1005006021054387.html",
    "image": "https://ae-pic-a1.aliexpress-media.com/kf/S5fa1eae684724efd982a04d09d9db5fa7.jpg",
    "price": 10.01,
    "old_price": 25.87,
    "currency": "EUR",
    "discount": "61%",
    "source": "aliexpress",
    "source_label": "AliExpress",
    "category": "Bolsas",
    "shop_name": "HUALONG Cycling Accessories Store Store",
    "rating": "95.9%",
    "sales": 1599,
    "commission_rate": "7.0%",
    "brand": "",
    "category_hint": "Bolsas",
    "discount_pct": 61,
    "recomendacion": 124
  },
  {
    "id": "amazon-gafas-fotocromaticas-1",
    "title": "X-TIGER Gafas Ciclismo Fotocromáticas",
    "category": "Gafas",
    "price": 29.99,
    "old_price": 39.99,
    "url": "https://www.amazon.es/dp/B0C2VJ55FV?tag=chollobici0a-21",
    "image": "/assets/placeholder-product.svg",
    "source": "amazon",
    "last_checked": "2026-04-25",
    "editor_pick": true,
    "asin": "B0C2VJ55FV",
    "brand": "",
    "category_hint": "Gafas",
    "discount_pct": 25,
    "source_label": "Amazon",
    "recomendacion": 64
  },
  {
    "id": "https://www.decathlon.es/es/p/zapatillas-ciclismo-gravel-500-negro-cordones-spd/192015/c382c382m8403017",
    "title": "Zapatillas Ciclismo Gravel 500 Negro Cordones SPD",
    "brand": "Decathlon",
    "category": "ciclismo",
    "category_hint": "Travesía todoterreno|Viaje todocamino|Btt travesía|Cicloturismo|Gravel",
    "image": "https://contents.mediadecathlon.com/p1600570/k$2ecb230b2550a468f86216c156536329/picture.jpg?f=300x300",
    "url": "https://www.decathlon.es/es/p/zapatillas-ciclismo-gravel-500-negro-cordones-spd/192015/c382c382m8403017",
    "affiliate_url": "https://afiliacion.decathlon.es/tracking/clk?fid=107&pca=8403017|Zapatillas Ciclismo Gravel 500 Negro Cordones SPD|&act=21712&gel=0&pub=42111&org=2615&url=https://www.decathlon.es/es/p/zapatillas-ciclismo-gravel-500-negro-cordones-spd/192015/c382c382m8403017",
    "source": "decathlon",
    "source_label": "Decathlon",
    "price": 54.99,
    "old_price": "",
    "discount_pct": 0,
    "recomendacion": 49,
    "detail_enabled": false,
    "sku": "8403017"
  },
  {
    "id": "1005006053104716",
    "title": "Luz LED de policía de hombro roja y azul con Clip, carga USB, advertencia intermitente, linterna de seguridad, luz de advertencia para bicicleta",
    "url": "https://s.click.aliexpress.com/e/_c3ctidGP",
    "affiliate_url": "https://s.click.aliexpress.com/e/_c3ctidGP",
    "product_detail_url": "https://es.aliexpress.com/item/1005006053104716.html",
    "image": "https://ae-pic-a1.aliexpress-media.com/kf/S90b84d33895c400cb8b06626c5d02e93U.jpg",
    "price": 3.89,
    "old_price": 11.79,
    "currency": "EUR",
    "discount": "67%",
    "source": "aliexpress",
    "source_label": "AliExpress",
    "category": "Luces",
    "shop_name": "FunDigi Home Store",
    "rating": "97.1%",
    "sales": 867,
    "commission_rate": "7.0%",
    "brand": "",
    "category_hint": "Luces",
    "discount_pct": 67,
    "recomendacion": 124
  },
  {
    "id": "amazon-ciclocomputador-magene-1",
    "title": "Magene C606 Pro Ciclocomputador GPS",
    "category": "Electrónica",
    "price": 69.99,
    "old_price": 89.99,
    "url": "https://www.amazon.es/dp/B0GHR2V8XV?tag=chollobici0a-21",
    "image": "https://m.media-amazon.com/images/I/61j1O5a7-HL._AC_SY300_SX300_QL70_ML2_.jpg",
    "source": "amazon",
    "last_checked": "2026-04-25",
    "editor_pick": false,
    "asin": "B0GHR2V8XV",
    "brand": "",
    "category_hint": "Electrónica",
    "discount_pct": 22,
    "source_label": "Amazon",
    "recomendacion": 47
  },
  {
    "id": "https://www.decathlon.es/es/p/bolsa-portaequipajes-bicicleta-advt-900-estanca-ipx6-14-l/358100/c407m8912342",
    "title": "Bolsa Portaequipajes Bicicleta ADVT 900 Estanca IPX6 14 l",
    "brand": "Decathlon",
    "category": "ciclismo",
    "category_hint": "Travesía todoterreno|Viaje todocamino|Btt all mountain|Btt cross country|Btt travesía|Ciclodeporte|Cicloturismo|Gravel|ciclismo urbano|Bicicleta urbana rápida",
    "image": "https://contents.mediadecathlon.com/p2885560/k$afd3776e78c56fb9db111e168c4d8a2f/picture.jpg?f=300x300",
    "url": "https://www.decathlon.es/es/p/bolsa-portaequipajes-bicicleta-advt-900-estanca-ipx6-14-l/358100/c407m8912342",
    "affiliate_url": "https://afiliacion.decathlon.es/tracking/clk?fid=107&pca=8912342|Bolsa Portaequipajes Bicicleta ADVT 900 Estanca IPX6 14 l|&act=21712&gel=0&pub=42111&org=2615&url=https://www.decathlon.es/es/p/bolsa-portaequipajes-bicicleta-advt-900-estanca-ipx6-14-l/358100/c407m8912342",
    "source": "decathlon",
    "source_label": "Decathlon",
    "price": 64.99,
    "old_price": "",
    "discount_pct": 0,
    "recomendacion": 49,
    "detail_enabled": false,
    "sku": "8912342"
  },
  {
    "id": "1005005864361452",
    "title": "Luz LED roja y azul de precaución de emergencia para policía con Clip, recargable por USB, linterna de seguridad intermitente para hombro, lámpara trasera para bicicleta",
    "url": "https://s.click.aliexpress.com/e/_c3Ft1V0n",
    "affiliate_url": "https://s.click.aliexpress.com/e/_c3Ft1V0n",
    "product_detail_url": "https://es.aliexpress.com/item/1005005864361452.html",
    "image": "https://ae-pic-a1.aliexpress-media.com/kf/S0942700ad9064d1f8c006b134c36b6e2K.jpg",
    "price": 4.49,
    "old_price": 13.61,
    "currency": "EUR",
    "discount": "67%",
    "source": "aliexpress",
    "source_label": "AliExpress",
    "category": "Luces",
    "shop_name": "FunDigi Home Store",
    "rating": "96.6%",
    "sales": 1047,
    "commission_rate": "7.0%",
    "brand": "",
    "category_hint": "Luces",
    "discount_pct": 67,
    "recomendacion": 124
  },
  {
    "id": "https://www.decathlon.es/es/p/maillot-ciclismo-mtb-expl-500-mujer-negro-verde-manga-larga/323574/c202c1m8577779",
    "title": "Maillot Ciclismo MTB Expl 500 Mujer Negro Verde Manga Larga",
    "brand": "Decathlon",
    "category": "ciclismo",
    "category_hint": "Travesía todoterreno|Viaje todocamino|Btt all mountain|Btt travesía",
    "image": "https://contents.mediadecathlon.com/p2342669/k$48d77dc3931521526e78338085cc6c27/picture.jpg?f=300x300",
    "url": "https://www.decathlon.es/es/p/maillot-ciclismo-mtb-expl-500-mujer-negro-verde-manga-larga/323574/c202c1m8577779",
    "affiliate_url": "https://afiliacion.decathlon.es/tracking/clk?fid=107&pca=8577779|Maillot Ciclismo MTB Expl 500 Mujer Negro Verde Manga Larga|&act=21712&gel=0&pub=42111&org=2615&url=https://www.decathlon.es/es/p/maillot-ciclismo-mtb-expl-500-mujer-negro-verde-manga-larga/323574/c202c1m8577779",
    "source": "decathlon",
    "source_label": "Decathlon",
    "price": 19.99,
    "old_price": "",
    "discount_pct": 0,
    "recomendacion": 49,
    "detail_enabled": false,
    "sku": "8577779"
  },
  {
    "id": "1005012052602180",
    "title": "Calas Compatibles Originales Shimano - SM-SH51 y SH56 Multi-Release para Pedales de Bicicleta de Montaña, Accesorios para Bicicleta Shimano Rockbros",
    "url": "https://s.click.aliexpress.com/s/fwx308cRD9Eny963e3KDdYxyIpNj8TXVr7saiF9Um5rMUg1kZtJALLnfa2LNXtiVgnxdD8Og6MmvwBoxhnSYQGM6r0c08U4TfX8DFGo7vviCuu3q62Q60OAhRZcqm3G8PtwM69xY7TOEWRrvulP5ukZQ4uQbBBtaVsdr6EffAqVmp3O5GyUANU2DoA3dJufNhDfh7KOlLgKIvRVhDxRESHLmea6fTE26gLUqKEUuuizJiLENrCbax94DZHDu8WhaXM9vQ86gzlqceNPO5w3vwXm4VrBF3x2lAMEl06wgNdTSMiT7cNG4HIdW0JxhF2kiDpOiDklobGncVGmlXIDomMHBlM8ufBH4xTEhgGQwllXda5f8nV5FPCNjyyWOZQHj6Qgg3UNKT5TRYNtdSmUDnbgBDiiN3R697xOnWjxCSwJ3rbeq5vASpVlMagSyRm0KZ8gsrmfO5GoBC7c2zj4NVjBbz8C9kOUhSmj88FuSeOLncBSxWXA0cfiEf3oZNNhymUB7cy166GgN5XNJUKpT3xaljHrV3VIMfERLL9NPjebI6raaA224nSgTOa3Uv4ZTlRAtgYs9u9U9qk0AzhhWrmvJe5RxyvobX6XRjZDjEINRPBbtykUd1fzaFabeQUWHCuCrliOkiigkokHk0Al9FBzeeimSsKZzazlNJsBsDvSuCt8AlowC1UCAqxqqag6HpPMxSCSB2Nl2weuM4WtsR6vH1mN8aUtnLDrYYWjlbxAPTilYBPskSPla54ILQooIYvkS9AnyO2InzpKIDLmhOe3KH6L0Jie5TWAD7suMAu6yRywLsgIsFDK8G60GVgQne1O9yIfoymt08XnQtDRA6zhL3RZaGiiRo2jqjw2mB4hifnTCcWxkC6WjUKoYsa2WDNtiI3G1hzUdrhGjFLhTnM6KJoGyNFB7BzKo3bXnptEGDYzJ0StAjD4k8AQfbi9PBFcWyEPWLFNev9Egbv",
    "affiliate_url": "https://s.click.aliexpress.com/s/fwx308cRD9Eny963e3KDdYxyIpNj8TXVr7saiF9Um5rMUg1kZtJALLnfa2LNXtiVgnxdD8Og6MmvwBoxhnSYQGM6r0c08U4TfX8DFGo7vviCuu3q62Q60OAhRZcqm3G8PtwM69xY7TOEWRrvulP5ukZQ4uQbBBtaVsdr6EffAqVmp3O5GyUANU2DoA3dJufNhDfh7KOlLgKIvRVhDxRESHLmea6fTE26gLUqKEUuuizJiLENrCbax94DZHDu8WhaXM9vQ86gzlqceNPO5w3vwXm4VrBF3x2lAMEl06wgNdTSMiT7cNG4HIdW0JxhF2kiDpOiDklobGncVGmlXIDomMHBlM8ufBH4xTEhgGQwllXda5f8nV5FPCNjyyWOZQHj6Qgg3UNKT5TRYNtdSmUDnbgBDiiN3R697xOnWjxCSwJ3rbeq5vASpVlMagSyRm0KZ8gsrmfO5GoBC7c2zj4NVjBbz8C9kOUhSmj88FuSeOLncBSxWXA0cfiEf3oZNNhymUB7cy166GgN5XNJUKpT3xaljHrV3VIMfERLL9NPjebI6raaA224nSgTOa3Uv4ZTlRAtgYs9u9U9qk0AzhhWrmvJe5RxyvobX6XRjZDjEINRPBbtykUd1fzaFabeQUWHCuCrliOkiigkokHk0Al9FBzeeimSsKZzazlNJsBsDvSuCt8AlowC1UCAqxqqag6HpPMxSCSB2Nl2weuM4WtsR6vH1mN8aUtnLDrYYWjlbxAPTilYBPskSPla54ILQooIYvkS9AnyO2InzpKIDLmhOe3KH6L0Jie5TWAD7suMAu6yRywLsgIsFDK8G60GVgQne1O9yIfoymt08XnQtDRA6zhL3RZaGiiRo2jqjw2mB4hifnTCcWxkC6WjUKoYsa2WDNtiI3G1hzUdrhGjFLhTnM6KJoGyNFB7BzKo3bXnptEGDYzJ0StAjD4k8AQfbi9PBFcWyEPWLFNev9Egbv",
    "product_detail_url": "https://es.aliexpress.com/item/1005012052602180.html",
    "image": "https://ae-pic-a1.aliexpress-media.com/kf/S565d9104a8d84778b569803af71d0841L.jpg",
    "price": 4.09,
    "old_price": 16.36,
    "currency": "EUR",
    "discount": "75%",
    "source": "aliexpress",
    "source_label": "AliExpress",
    "category": "Componentes",
    "shop_name": "Shop1105389668 Store",
    "rating": "",
    "sales": 3,
    "commission_rate": "7.0%",
    "brand": "",
    "category_hint": "Componentes",
    "discount_pct": 75,
    "recomendacion": 123
  },
  {
    "id": "https://www.decathlon.es/es/p/maillot-ciclismo-mtb-500-beis-manga-corta-transpirable/359711/c70c76m8974496",
    "title": "Maillot Ciclismo MTB 500 Beis Manga Corta Transpirable",
    "brand": "Decathlon",
    "category": "ciclismo",
    "category_hint": "Travesía todoterreno|Btt all mountain|Btt travesía|Gravel",
    "image": "https://contents.mediadecathlon.com/p3102918/k$d5e464b099b4625d0ea02c4dc1a1623d/picture.jpg?f=300x300",
    "url": "https://www.decathlon.es/es/p/maillot-ciclismo-mtb-500-beis-manga-corta-transpirable/359711/c70c76m8974496",
    "affiliate_url": "https://afiliacion.decathlon.es/tracking/clk?fid=107&pca=8974496|Maillot Ciclismo MTB 500 Beis Manga Corta Transpirable|&act=21712&gel=0&pub=42111&org=2615&url=https://www.decathlon.es/es/p/maillot-ciclismo-mtb-500-beis-manga-corta-transpirable/359711/c70c76m8974496",
    "source": "decathlon",
    "source_label": "Decathlon",
    "price": 19.99,
    "old_price": "",
    "discount_pct": 0,
    "recomendacion": 49,
    "detail_enabled": false,
    "sku": "8974496"
  },
  {
    "id": "1005012078380288",
    "title": "ESLNF-pedales para bicicleta de montaña, calzado con clip autoblocante para sistema SPD SL con placa de bloqueo, accesorios para bicicleta de montaña",
    "url": "https://s.click.aliexpress.com/e/_c36SorZ1",
    "affiliate_url": "https://s.click.aliexpress.com/e/_c36SorZ1",
    "product_detail_url": "https://es.aliexpress.com/item/1005012078380288.html",
    "image": "https://ae-pic-a1.aliexpress-media.com/kf/S93f6859420ac4fbb9f170f0c2fb06a07b.jpg",
    "price": 2.66,
    "old_price": 8.84,
    "currency": "EUR",
    "discount": "70%",
    "source": "aliexpress",
    "source_label": "AliExpress",
    "category": "Componentes",
    "shop_name": "ESLNF Flagship Store",
    "rating": "",
    "sales": 0,
    "commission_rate": "7.0%",
    "brand": "",
    "category_hint": "Componentes",
    "discount_pct": 70,
    "recomendacion": 122
  },
  {
    "id": "https://www.decathlon.es/es/p/pantalon-corto-ciclismo-mtb-expl-700-mujer-rosa/305572/c16c382m8668141",
    "title": "Pantalón Corto Ciclismo MTB Expl 700 Mujer Rosa",
    "brand": "Decathlon",
    "category": "ciclismo",
    "category_hint": "Btt travesía",
    "image": "https://contents.mediadecathlon.com/p2396121/k$201fdb5a2be6e61d8bf8e0793c4fec26/picture.jpg?f=300x300",
    "url": "https://www.decathlon.es/es/p/pantalon-corto-ciclismo-mtb-expl-700-mujer-rosa/305572/c16c382m8668141",
    "affiliate_url": "https://afiliacion.decathlon.es/tracking/clk?fid=107&pca=8668141|Pantalón Corto Ciclismo MTB Expl 700 Mujer Rosa|&act=21712&gel=0&pub=42111&org=2615&url=https://www.decathlon.es/es/p/pantalon-corto-ciclismo-mtb-expl-700-mujer-rosa/305572/c16c382m8668141",
    "source": "decathlon",
    "source_label": "Decathlon",
    "price": 20.99,
    "old_price": "",
    "discount_pct": 0,
    "recomendacion": 49,
    "detail_enabled": false,
    "sku": "8668141"
  },
  {
    "id": "1005005864360932",
    "title": "Guantes de pantalla táctil de invierno tejidos con cable negro cálido a la moda con forro polar al por mayor",
    "url": "https://s.click.aliexpress.com/e/_c3Vu7QZN",
    "affiliate_url": "https://s.click.aliexpress.com/e/_c3Vu7QZN",
    "product_detail_url": "https://es.aliexpress.com/item/1005005864360932.html",
    "image": "https://ae-pic-a1.aliexpress-media.com/kf/S53bc0d2d83c648a68159e2e48f1a6058O.jpg",
    "price": 3.79,
    "old_price": 15.16,
    "currency": "EUR",
    "discount": "75%",
    "source": "aliexpress",
    "source_label": "AliExpress",
    "category": "Accesorios",
    "shop_name": "Shop1102890092 Store",
    "rating": "95.5%",
    "sales": 11693,
    "commission_rate": "7.0%",
    "brand": "",
    "category_hint": "Accesorios",
    "discount_pct": 75,
    "recomendacion": 122
  },
  {
    "id": "https://www.decathlon.es/es/p/pantalon-corto-ciclismo-mtb-expl-700-mujer-negro/305572/c382m8736356",
    "title": "Pantalón Corto Ciclismo MTB Expl 700 Mujer Negro",
    "brand": "Decathlon",
    "category": "ciclismo",
    "category_hint": "Btt travesía",
    "image": "https://contents.mediadecathlon.com/p2408855/k$337f7cd2c9eab23d382ec665fe934bbe/picture.jpg?f=300x300",
    "url": "https://www.decathlon.es/es/p/pantalon-corto-ciclismo-mtb-expl-700-mujer-negro/305572/c382m8736356",
    "affiliate_url": "https://afiliacion.decathlon.es/tracking/clk?fid=107&pca=8736356|Pantalón Corto Ciclismo MTB Expl 700 Mujer Negro|&act=21712&gel=0&pub=42111&org=2615&url=https://www.decathlon.es/es/p/pantalon-corto-ciclismo-mtb-expl-700-mujer-negro/305572/c382m8736356",
    "source": "decathlon",
    "source_label": "Decathlon",
    "price": 21.99,
    "old_price": "",
    "discount_pct": 0,
    "recomendacion": 49,
    "detail_enabled": false,
    "sku": "8736356"
  },
  {
    "id": "1005007391261966",
    "title": "Raudax-Camiseta de Ciclismo de 6 colores, camiseta de manga corta para bicicleta de carretera, camisetas de verano para bicicleta, novedad",
    "url": "https://s.click.aliexpress.com/e/_c3hrrCNl",
    "affiliate_url": "https://s.click.aliexpress.com/e/_c3hrrCNl",
    "product_detail_url": "https://es.aliexpress.com/item/1005007391261966.html",
    "image": "https://ae-pic-a1.aliexpress-media.com/kf/S9d448e8794c7401f99474e87cdd9570fL.jpg",
    "price": 10.88,
    "old_price": 28.08,
    "currency": "EUR",
    "discount": "61%",
    "source": "aliexpress",
    "source_label": "AliExpress",
    "category": "Ropa",
    "shop_name": "RAUDAX Official Store",
    "rating": "94.2%",
    "sales": 3154,
    "commission_rate": "7.0%",
    "brand": "",
    "category_hint": "Ropa",
    "discount_pct": 61,
    "recomendacion": 119
  },
  {
    "id": "https://www.decathlon.es/es/p/pantalon-corto-ciclismo-mtb-cargo-mujer-burdeos/330705/c15m8668137",
    "title": "Pantalón Corto Ciclismo MTB Cargo Mujer Burdeos",
    "brand": "Decathlon",
    "category": "ciclismo",
    "category_hint": "Btt travesía",
    "image": "https://contents.mediadecathlon.com/p2410321/k$e82c944643ae74b2befe578c7ddb06de/picture.jpg?f=300x300",
    "url": "https://www.decathlon.es/es/p/pantalon-corto-ciclismo-mtb-cargo-mujer-burdeos/330705/c15m8668137",
    "affiliate_url": "https://afiliacion.decathlon.es/tracking/clk?fid=107&pca=8668137|Pantalón Corto Ciclismo MTB Cargo Mujer Burdeos|&act=21712&gel=0&pub=42111&org=2615&url=https://www.decathlon.es/es/p/pantalon-corto-ciclismo-mtb-cargo-mujer-burdeos/330705/c15m8668137",
    "source": "decathlon",
    "source_label": "Decathlon",
    "price": 27.99,
    "old_price": "",
    "discount_pct": 0,
    "recomendacion": 49,
    "detail_enabled": false,
    "sku": "8668137"
  },
  {
    "id": "1005006101518971",
    "title": "Guantes de invierno para hombre y mujer, manoplas cálidas de terciopelo para deportes al aire libre, correr y esquiar, resistentes al agua y al frío",
    "url": "https://s.click.aliexpress.com/e/_c4cuFbyn",
    "affiliate_url": "https://s.click.aliexpress.com/e/_c4cuFbyn",
    "product_detail_url": "https://es.aliexpress.com/item/1005006101518971.html",
    "image": "https://ae-pic-a1.aliexpress-media.com/kf/Sb425876280704153aa94ae727af22fc2P.jpg",
    "price": 3.59,
    "old_price": 14.36,
    "currency": "EUR",
    "discount": "75%",
    "source": "aliexpress",
    "source_label": "AliExpress",
    "category": "Accesorios",
    "shop_name": "GAFASTWO Official Store",
    "rating": "95.9%",
    "sales": 3198,
    "commission_rate": "7.0%",
    "brand": "",
    "category_hint": "Accesorios",
    "discount_pct": 75,
    "recomendacion": 119
  },
  {
    "id": "https://www.decathlon.es/es/p/maillot-mtb-500-hombre-marron-cobrizo-manga-corta-transpirable/356996/c101m8926303",
    "title": "Maillot MTB 500 Hombre Marrón Cobrizo Manga Corta Transpirable",
    "brand": "Decathlon",
    "category": "ciclismo",
    "category_hint": "Travesía todoterreno|Viaje todocamino|Btt travesía|Gravel",
    "image": "https://contents.mediadecathlon.com/p3102965/k$e7b49dcff7bd11a5c9e1f102e233a0d9/picture.jpg?f=300x300",
    "url": "https://www.decathlon.es/es/p/maillot-mtb-500-hombre-marron-cobrizo-manga-corta-transpirable/356996/c101m8926303",
    "affiliate_url": "https://afiliacion.decathlon.es/tracking/clk?fid=107&pca=8926303|Maillot MTB 500 Hombre Marrón Cobrizo Manga Corta Transpirable|&act=21712&gel=0&pub=42111&org=2615&url=https://www.decathlon.es/es/p/maillot-mtb-500-hombre-marron-cobrizo-manga-corta-transpirable/356996/c101m8926303",
    "source": "decathlon",
    "source_label": "Decathlon",
    "price": 29.99,
    "old_price": "",
    "discount_pct": 0,
    "recomendacion": 49,
    "detail_enabled": false,
    "sku": "8926303"
  },
  {
    "id": "1005005209973776",
    "title": "RYET-sillín de bicicleta con estampado 3D, ultraligero, de fibra de carbono, hueco, cómodo, transpirable, para bicicleta de montaña, grava, piezas de asiento de ciclismo",
    "url": "https://s.click.aliexpress.com/e/_c3voVpVt",
    "affiliate_url": "https://s.click.aliexpress.com/e/_c3voVpVt",
    "product_detail_url": "https://es.aliexpress.com/item/1005005209973776.html",
    "image": "https://ae-pic-a1.aliexpress-media.com/kf/S3ede193d6df34a7fa837fc4c8ddd78fcn.png",
    "price": 36.99,
    "old_price": 86.02,
    "currency": "EUR",
    "discount": "56%",
    "source": "aliexpress",
    "source_label": "AliExpress",
    "category": "Bolsas",
    "shop_name": "LEXON Official Store",
    "rating": "95.9%",
    "sales": 7051,
    "commission_rate": "7.0%",
    "brand": "",
    "category_hint": "Bolsas",
    "discount_pct": 56,
    "recomendacion": 116
  },
  {
    "id": "https://www.decathlon.es/es/p/maillot-ciclismo-mtb-500-hombre-amarillo-cargo-manga-corta-transpirable/356996/c339m8979273",
    "title": "Maillot Ciclismo MTB 500 Hombre Amarillo Cargo Manga Corta Transpirable",
    "brand": "Decathlon",
    "category": "ciclismo",
    "category_hint": "Travesía todoterreno|Viaje todocamino|Btt travesía|Gravel",
    "image": "https://contents.mediadecathlon.com/p3102914/k$d791aa28df63144d0d3a2c0511e62265/picture.jpg?f=300x300",
    "url": "https://www.decathlon.es/es/p/maillot-ciclismo-mtb-500-hombre-amarillo-cargo-manga-corta-transpirable/356996/c339m8979273",
    "affiliate_url": "https://afiliacion.decathlon.es/tracking/clk?fid=107&pca=8979273|Maillot Ciclismo MTB 500 Hombre Amarillo Cargo Manga Corta Transpirable|&act=21712&gel=0&pub=42111&org=2615&url=https://www.decathlon.es/es/p/maillot-ciclismo-mtb-500-hombre-amarillo-cargo-manga-corta-transpirable/356996/c339m8979273",
    "source": "decathlon",
    "source_label": "Decathlon",
    "price": 29.99,
    "old_price": "",
    "discount_pct": 0,
    "recomendacion": 49,
    "detail_enabled": false,
    "sku": "8979273"
  },
  {
    "id": "1005005999457783",
    "title": "Juego de luces delanteras para bicicleta con luz trasera, recargable por USB, fácil de instalar, 3 modos, accesorios para bicicleta de carretera MTB",
    "url": "https://s.click.aliexpress.com/e/_c37imbO7",
    "affiliate_url": "https://s.click.aliexpress.com/e/_c37imbO7",
    "product_detail_url": "https://es.aliexpress.com/item/1005005999457783.html",
    "image": "https://ae-pic-a1.aliexpress-media.com/kf/S4c0c6041de93458285938b42a8952b34p.jpg",
    "price": 1.79,
    "old_price": 4.41,
    "currency": "EUR",
    "discount": "59%",
    "source": "aliexpress",
    "source_label": "AliExpress",
    "category": "Luces",
    "shop_name": "AiYing Cycling Equipment Store",
    "rating": "91.9%",
    "sales": 1797,
    "commission_rate": "7.0%",
    "brand": "",
    "category_hint": "Luces",
    "discount_pct": 59,
    "recomendacion": 116
  },
  {
    "id": "https://www.decathlon.es/es/p/maillot-mtb-unisex-transpirable/337010/c117c117m8677531",
    "title": "Maillot MTB Unisex Transpirable",
    "brand": "Decathlon",
    "category": "ciclismo",
    "category_hint": "Btt all mountain",
    "image": "https://contents.mediadecathlon.com/p3102994/k$8b664ff650a53050d0b2001297fc0556/picture.jpg?f=300x300",
    "url": "https://www.decathlon.es/es/p/maillot-mtb-unisex-transpirable/337010/c117c117m8677531",
    "affiliate_url": "https://afiliacion.decathlon.es/tracking/clk?fid=107&pca=8677531|Maillot MTB Unisex Transpirable|&act=21712&gel=0&pub=42111&org=2615&url=https://www.decathlon.es/es/p/maillot-mtb-unisex-transpirable/337010/c117c117m8677531",
    "source": "decathlon",
    "source_label": "Decathlon",
    "price": 29.99,
    "old_price": "",
    "discount_pct": 0,
    "recomendacion": 49,
    "detail_enabled": false,
    "sku": "8677531"
  },
  {
    "id": "1005005907906909",
    "title": "Raudax Team 2024 hombres verano manga corta Ciclismo Jersey conjunto MTB Maillot Ropa Ciclismo Ropa de bicicleta Ropa de Ciclismo transpirable",
    "url": "https://s.click.aliexpress.com/e/_c41kQ7O7",
    "affiliate_url": "https://s.click.aliexpress.com/e/_c41kQ7O7",
    "product_detail_url": "https://es.aliexpress.com/item/1005005907906909.html",
    "image": "https://ae-pic-a1.aliexpress-media.com/kf/S4e8045811f9f43dd9a7d905bb58f0eaec.jpg",
    "price": 11.16,
    "old_price": 27.26,
    "currency": "EUR",
    "discount": "59%",
    "source": "aliexpress",
    "source_label": "AliExpress",
    "category": "Ropa",
    "shop_name": "RAUDAX Official Store",
    "rating": "94.2%",
    "sales": 1444,
    "commission_rate": "7.0%",
    "brand": "",
    "category_hint": "Ropa",
    "discount_pct": 59,
    "recomendacion": 116
  },
  {
    "id": "https://www.decathlon.es/es/p/guantes-ciclismo-mtb-900-negro-proteccion-d3o/333463/c382m8646536",
    "title": "Guantes Ciclismo MTB 900 Negro Protección D3O®",
    "brand": "Decathlon",
    "category": "ciclismo",
    "category_hint": "descenso BTT|Btt all mountain|Btt travesía|BTT Enduro",
    "image": "https://contents.mediadecathlon.com/p2854622/k$51ab88d28c95b900f989a92d8cc02f84/picture.jpg?f=300x300",
    "url": "https://www.decathlon.es/es/p/guantes-ciclismo-mtb-900-negro-proteccion-d3o/333463/c382m8646536",
    "affiliate_url": "https://afiliacion.decathlon.es/tracking/clk?fid=107&pca=8646536|Guantes Ciclismo MTB 900 Negro Protección D3O®|&act=21712&gel=0&pub=42111&org=2615&url=https://www.decathlon.es/es/p/guantes-ciclismo-mtb-900-negro-proteccion-d3o/333463/c382m8646536",
    "source": "decathlon",
    "source_label": "Decathlon",
    "price": 29.99,
    "old_price": "",
    "discount_pct": 0,
    "recomendacion": 49,
    "detail_enabled": false,
    "sku": "8646536"
  },
  {
    "id": "1005005257777214",
    "title": "ELITAONE MTB tija de sillín de carbono 27,2/30,9/31,6mm Offset 20mm tija de sillín de bicicleta de carretera con cubierta de Base de fibra de carbono",
    "url": "https://s.click.aliexpress.com/e/_c4tHS3bV",
    "affiliate_url": "https://s.click.aliexpress.com/e/_c4tHS3bV",
    "product_detail_url": "https://es.aliexpress.com/item/1005005257777214.html",
    "image": "https://ae-pic-a1.aliexpress-media.com/kf/S0c3024c10b9a4f0bacd4ef099d523787f.jpg",
    "price": 20.92,
    "old_price": 48.35,
    "currency": "EUR",
    "discount": "56%",
    "source": "aliexpress",
    "source_label": "AliExpress",
    "category": "Bolsas",
    "shop_name": "ELITA ONE Carbon fibre bike Store",
    "rating": "96.5%",
    "sales": 1411,
    "commission_rate": "7.0%",
    "brand": "",
    "category_hint": "Bolsas",
    "discount_pct": 56,
    "recomendacion": 115
  },
  {
    "id": "https://www.decathlon.es/es/p/cortaviento-bici-mtb-mujer-azul-marino/330682/c364m8615581",
    "title": "Cortaviento Bici MTB Mujer Azul Marino",
    "brand": "Decathlon",
    "category": "ciclismo",
    "category_hint": "Btt travesía",
    "image": "https://contents.mediadecathlon.com/p2408836/k$3579cc3de586776d88f1f8bb3798e26a/picture.jpg?f=300x300",
    "url": "https://www.decathlon.es/es/p/cortaviento-bici-mtb-mujer-azul-marino/330682/c364m8615581",
    "affiliate_url": "https://afiliacion.decathlon.es/tracking/clk?fid=107&pca=8615581|Cortaviento Bici MTB Mujer Azul Marino|&act=21712&gel=0&pub=42111&org=2615&url=https://www.decathlon.es/es/p/cortaviento-bici-mtb-mujer-azul-marino/330682/c364m8615581",
    "source": "decathlon",
    "source_label": "Decathlon",
    "price": 29.99,
    "old_price": "",
    "discount_pct": 0,
    "recomendacion": 49,
    "detail_enabled": false,
    "sku": "8615581"
  },
  {
    "id": "1005005349509484",
    "title": "Luz trasera para bicicleta, luces traseras ultrabrillantes recargables por USB, aptas para bicicleta, fácil de instalar para luz de seguridad en ciclismo",
    "url": "https://s.click.aliexpress.com/e/_c3za6JPz",
    "affiliate_url": "https://s.click.aliexpress.com/e/_c3za6JPz",
    "product_detail_url": "https://es.aliexpress.com/item/1005005349509484.html",
    "image": "https://ae-pic-a1.aliexpress-media.com/kf/Sa1b1afb62ab542909ee940021a3ec71cW.jpg",
    "price": 2.12,
    "old_price": 5.03,
    "currency": "EUR",
    "discount": "57%",
    "source": "aliexpress",
    "source_label": "AliExpress",
    "category": "Luces",
    "shop_name": "Cycle Zone Outdoor Store",
    "rating": "94.1%",
    "sales": 3312,
    "commission_rate": "7.0%",
    "brand": "",
    "category_hint": "Luces",
    "discount_pct": 57,
    "recomendacion": 115
  },
  {
    "id": "https://www.decathlon.es/es/p/zapatillas-ciclismo-gravel-900-impermeables/307299/c382c259m8544057",
    "title": "Zapatillas Ciclismo Gravel 900 Impermeables",
    "brand": "Decathlon",
    "category": "ciclismo",
    "category_hint": "Cicloturismo|Gravel",
    "image": "https://contents.mediadecathlon.com/p2762742/k$f996bd9ec2dce1f25c313ed523c2db68/picture.jpg?f=300x300",
    "url": "https://www.decathlon.es/es/p/zapatillas-ciclismo-gravel-900-impermeables/307299/c382c259m8544057",
    "affiliate_url": "https://afiliacion.decathlon.es/tracking/clk?fid=107&pca=8544057|Zapatillas Ciclismo Gravel 900 Impermeables|&act=21712&gel=0&pub=42111&org=2615&url=https://www.decathlon.es/es/p/zapatillas-ciclismo-gravel-900-impermeables/307299/c382c259m8544057",
    "source": "decathlon",
    "source_label": "Decathlon",
    "price": 89.99,
    "old_price": "",
    "discount_pct": 0,
    "recomendacion": 47,
    "detail_enabled": false,
    "sku": "8544057"
  },
  {
    "id": "1005006883372689",
    "title": "BUCKLOS Pedal de bicicleta plataforma de Pedal ultraligera para bicicleta de montaña de carretera rodamientos sellados de nailon antideslizantes pedales planos pieza de bicicleta MTB",
    "url": "https://s.click.aliexpress.com/e/_c3Rma6IP",
    "affiliate_url": "https://s.click.aliexpress.com/e/_c3Rma6IP",
    "product_detail_url": "https://es.aliexpress.com/item/1005006883372689.html",
    "image": "https://ae-pic-a1.aliexpress-media.com/kf/Scede68352bc9436392e645120508c238d.jpg",
    "price": 14.45,
    "old_price": 33.62,
    "currency": "EUR",
    "discount": "57%",
    "source": "aliexpress",
    "source_label": "AliExpress",
    "category": "Componentes",
    "shop_name": "Hangtu Sports Store",
    "rating": "96.6%",
    "sales": 2859,
    "commission_rate": "7.0%",
    "brand": "",
    "category_hint": "Componentes",
    "discount_pct": 57,
    "recomendacion": 115
  },
  {
    "id": "https://www.decathlon.es/es/p/chubasquero-ciclismo-mujer-van-rysel-racer-amarillo/325513/c132m8619511",
    "title": "Chubasquero ciclismo mujer Van Rysel Racer amarillo",
    "brand": "Decathlon",
    "category": "ciclismo",
    "category_hint": "Ciclodeporte",
    "image": "https://contents.mediadecathlon.com/p2993432/k$9b4b8ae8e7cbe0f44f599aad2c6ffc5f/picture.jpg?f=300x300",
    "url": "https://www.decathlon.es/es/p/chubasquero-ciclismo-mujer-van-rysel-racer-amarillo/325513/c132m8619511",
    "affiliate_url": "https://afiliacion.decathlon.es/tracking/clk?fid=107&pca=8619511|Chubasquero ciclismo mujer Van Rysel Racer amarillo|&act=21712&gel=0&pub=42111&org=2615&url=https://www.decathlon.es/es/p/chubasquero-ciclismo-mujer-van-rysel-racer-amarillo/325513/c132m8619511",
    "source": "decathlon",
    "source_label": "Decathlon",
    "price": 34.99,
    "old_price": "",
    "discount_pct": 0,
    "recomendacion": 46,
    "detail_enabled": false,
    "sku": "8619511"
  },
  {
    "id": "1005006146531779",
    "title": "X-TIGER-cubierta térmica para zapatos de ciclismo, forro polar para invierno, para bicicleta de montaña, para hombre y mujer",
    "url": "https://s.click.aliexpress.com/e/_c3sqGufD",
    "affiliate_url": "https://s.click.aliexpress.com/e/_c3sqGufD",
    "product_detail_url": "https://es.aliexpress.com/item/1005006146531779.html",
    "image": "https://ae-pic-a1.aliexpress-media.com/kf/Sdda5fc9802eb4f30bbcc7e1ae3f4acccb.jpg",
    "price": 4.69,
    "old_price": 10.2,
    "currency": "EUR",
    "discount": "54%",
    "source": "aliexpress",
    "source_label": "AliExpress",
    "category": "Ropa",
    "shop_name": "X-TIGER Cycling Store",
    "rating": "89.4%",
    "sales": 7492,
    "commission_rate": "7.0%",
    "brand": "",
    "category_hint": "Ropa",
    "discount_pct": 54,
    "recomendacion": 115
  },
  {
    "id": "https://www.decathlon.es/es/p/bicicleta-spidey-sin-pedales-regulable-en-altura-max-20-kg-cd/X9024524/m9024524",
    "title": "Bicicleta Spidey sin pedales regulable en altura máx. 20 kg -CD",
    "brand": "Decathlon",
    "category": "ciclismo",
    "category_hint": "ciclismo infantil",
    "image": "https://contents.mediadecathlon.com/p3039925/k$8a95e98d60a56fa05c76e08970c1e6e3/picture.jpg?f=300x300",
    "url": "https://www.decathlon.es/es/p/bicicleta-spidey-sin-pedales-regulable-en-altura-max-20-kg-cd/X9024524/m9024524",
    "affiliate_url": "https://afiliacion.decathlon.es/tracking/clk?fid=107&pca=9024524|Bicicleta Spidey sin pedales regulable en altura máx. 20 kg -CD|&act=21712&gel=0&pub=42111&org=2615&url=https://www.decathlon.es/es/p/bicicleta-spidey-sin-pedales-regulable-en-altura-max-20-kg-cd/X9024524/m9024524",
    "source": "decathlon",
    "source_label": "Decathlon",
    "price": 39.99,
    "old_price": "",
    "discount_pct": 0,
    "recomendacion": 46,
    "detail_enabled": false,
    "sku": "9024524"
  },
  {
    "id": "1005005366045125",
    "title": "Guantes de trabajo ligeros multiusos de alto rendimiento para hombres y mujeres pantalla táctil transpirable y de alta destreza agarre excelente",
    "url": "https://s.click.aliexpress.com/e/_c2uIv7JH",
    "affiliate_url": "https://s.click.aliexpress.com/e/_c2uIv7JH",
    "product_detail_url": "https://es.aliexpress.com/item/1005005366045125.html",
    "image": "https://ae-pic-a1.aliexpress-media.com/kf/Sd12673bcba3541ab922cff87f51e24dcL.jpg",
    "price": 3.79,
    "old_price": 10.7,
    "currency": "EUR",
    "discount": "64%",
    "source": "aliexpress",
    "source_label": "AliExpress",
    "category": "Accesorios",
    "shop_name": "FOUR-AM GLOVES Store",
    "rating": "95.8%",
    "sales": 11906,
    "commission_rate": "7.0%",
    "brand": "",
    "category_hint": "Accesorios",
    "discount_pct": 64,
    "recomendacion": 115
  },
  {
    "id": "https://www.decathlon.es/es/p/culotte-corto-bicicleta-carretera-sin-tirantes-menstrual-mujer-edr-negro/349681/c382m8828311",
    "title": "Culotte Corto Bicicleta Carretera sin Tirantes Menstrual Mujer EDR Negro",
    "brand": "Decathlon",
    "category": "ciclismo",
    "category_hint": "Ciclodeporte|Cicloturismo|Gravel|turbo trainer",
    "image": "https://contents.mediadecathlon.com/p3043217/k$ec0b9926eaca93e093656336fb4bdd10/picture.jpg?f=300x300",
    "url": "https://www.decathlon.es/es/p/culotte-corto-bicicleta-carretera-sin-tirantes-menstrual-mujer-edr-negro/349681/c382m8828311",
    "affiliate_url": "https://afiliacion.decathlon.es/tracking/clk?fid=107&pca=8828311|Culotte Corto Bicicleta Carretera sin Tirantes Menstrual Mujer EDR Negro|&act=21712&gel=0&pub=42111&org=2615&url=https://www.decathlon.es/es/p/culotte-corto-bicicleta-carretera-sin-tirantes-menstrual-mujer-edr-negro/349681/c382m8828311",
    "source": "decathlon",
    "source_label": "Decathlon",
    "price": 39.99,
    "old_price": "",
    "discount_pct": 0,
    "recomendacion": 46,
    "detail_enabled": false,
    "sku": "8828311"
  },
  {
    "id": "https://www.decathlon.es/es/p/pantalon-corto-ciclismo-mtb-cargo-mujer-negro/330705/c382m8615620",
    "title": "Pantalón Corto Ciclismo MTB Cargo Mujer Negro",
    "brand": "Decathlon",
    "category": "ciclismo",
    "category_hint": "Btt travesía",
    "image": "https://contents.mediadecathlon.com/p2408843/k$9c654e740acb18eb21ca1992590981c9/picture.jpg?f=300x300",
    "url": "https://www.decathlon.es/es/p/pantalon-corto-ciclismo-mtb-cargo-mujer-negro/330705/c382m8615620",
    "affiliate_url": "https://afiliacion.decathlon.es/tracking/clk?fid=107&pca=8615620|Pantalón Corto Ciclismo MTB Cargo Mujer Negro|&act=21712&gel=0&pub=42111&org=2615&url=https://www.decathlon.es/es/p/pantalon-corto-ciclismo-mtb-cargo-mujer-negro/330705/c382m8615620",
    "source": "decathlon",
    "source_label": "Decathlon",
    "price": 39.99,
    "old_price": "",
    "discount_pct": 0,
    "recomendacion": 46,
    "detail_enabled": false,
    "sku": "8615620"
  },
  {
    "id": "https://www.decathlon.es/es/p/bicicleta-infantil-kinderkraft-2way-next-2022-rose-pink-cd/X8993544/m8993544",
    "title": "Bicicleta Infantil Kinderkraft 2WAY NEXT 2022 rose pink - CD",
    "brand": "Decathlon",
    "category": "ciclismo",
    "category_hint": "ciclismo infantil",
    "image": "https://contents.mediadecathlon.com/p2936751/k$1f67db8b9c6d8bf66cd499479e1bb981/picture.jpg?f=300x300",
    "url": "https://www.decathlon.es/es/p/bicicleta-infantil-kinderkraft-2way-next-2022-rose-pink-cd/X8993544/m8993544",
    "affiliate_url": "https://afiliacion.decathlon.es/tracking/clk?fid=107&pca=8993544|Bicicleta Infantil Kinderkraft 2WAY NEXT 2022 rose pink - CD|&act=21712&gel=0&pub=42111&org=2615&url=https://www.decathlon.es/es/p/bicicleta-infantil-kinderkraft-2way-next-2022-rose-pink-cd/X8993544/m8993544",
    "source": "decathlon",
    "source_label": "Decathlon",
    "price": 39.99,
    "old_price": "",
    "discount_pct": 0,
    "recomendacion": 46,
    "detail_enabled": false,
    "sku": "8993544"
  },
  {
    "id": "https://www.decathlon.es/es/p/bicicleta-bluey-sin-pedales-regulable-en-altura-max-20-kg/X9024520/m9024520",
    "title": "Bicicleta Bluey sin pedales regulable en altura máx. 20 kg",
    "brand": "Decathlon",
    "category": "ciclismo",
    "category_hint": "ciclismo infantil",
    "image": "https://contents.mediadecathlon.com/p3039669/k$d8673e0a38f7e3015971b726ba4cab4b/picture.jpg?f=300x300",
    "url": "https://www.decathlon.es/es/p/bicicleta-bluey-sin-pedales-regulable-en-altura-max-20-kg/X9024520/m9024520",
    "affiliate_url": "https://afiliacion.decathlon.es/tracking/clk?fid=107&pca=9024520|Bicicleta Bluey sin pedales regulable en altura máx. 20 kg|&act=21712&gel=0&pub=42111&org=2615&url=https://www.decathlon.es/es/p/bicicleta-bluey-sin-pedales-regulable-en-altura-max-20-kg/X9024520/m9024520",
    "source": "decathlon",
    "source_label": "Decathlon",
    "price": 44.99,
    "old_price": "",
    "discount_pct": 0,
    "recomendacion": 46,
    "detail_enabled": false,
    "sku": "9024520"
  },
  {
    "id": "https://www.decathlon.es/es/p/bicicleta-la-patrulla-canina-sin-pedales-regulable-en-altura-max-20-kg-cd/X9024521/m9024521",
    "title": "Bicicleta La Patrulla Canina sin pedales regulable en altura máx. 20 kg - CD",
    "brand": "Decathlon",
    "category": "ciclismo",
    "category_hint": "ciclismo infantil",
    "image": "https://contents.mediadecathlon.com/p3039771/k$be077902aa7c5d75acdbb80abfb245bc/picture.jpg?f=300x300",
    "url": "https://www.decathlon.es/es/p/bicicleta-la-patrulla-canina-sin-pedales-regulable-en-altura-max-20-kg-cd/X9024521/m9024521",
    "affiliate_url": "https://afiliacion.decathlon.es/tracking/clk?fid=107&pca=9024521|Bicicleta La Patrulla Canina sin pedales regulable en altura máx. 20 kg - CD|&act=21712&gel=0&pub=42111&org=2615&url=https://www.decathlon.es/es/p/bicicleta-la-patrulla-canina-sin-pedales-regulable-en-altura-max-20-kg-cd/X9024521/m9024521",
    "source": "decathlon",
    "source_label": "Decathlon",
    "price": 44.99,
    "old_price": "",
    "discount_pct": 0,
    "recomendacion": 46,
    "detail_enabled": false,
    "sku": "9024521"
  },
  {
    "id": "https://www.decathlon.es/es/p/maillot-ciclismo-carretera-edr-mujer-manga-larga-entretiempo/344263/c219m8935795",
    "title": "Maillot Ciclismo Carretera EDR Mujer Manga Larga Entretiempo",
    "brand": "Decathlon",
    "category": "ciclismo",
    "category_hint": "Ciclodeporte",
    "image": "https://contents.mediadecathlon.com/p2993351/k$c2cfe136ef36cfe1c80533af7bfcd43e/picture.jpg?f=300x300",
    "url": "https://www.decathlon.es/es/p/maillot-ciclismo-carretera-edr-mujer-manga-larga-entretiempo/344263/c219m8935795",
    "affiliate_url": "https://afiliacion.decathlon.es/tracking/clk?fid=107&pca=8935795|Maillot Ciclismo Carretera EDR Mujer Manga Larga Entretiempo|&act=21712&gel=0&pub=42111&org=2615&url=https://www.decathlon.es/es/p/maillot-ciclismo-carretera-edr-mujer-manga-larga-entretiempo/344263/c219m8935795",
    "source": "decathlon",
    "source_label": "Decathlon",
    "price": 44.99,
    "old_price": "",
    "discount_pct": 0,
    "recomendacion": 46,
    "detail_enabled": false,
    "sku": "8935795"
  },
  {
    "id": "https://www.decathlon.es/es/p/culotte-interior-mtb-all-mountain-enduro-feel-proteccion-d3o/359920/c382m8927322",
    "title": "Culotte Interior MTB All Mountain Enduro Feel Protección D3O®",
    "brand": "Decathlon",
    "category": "ciclismo",
    "category_hint": "Btt all mountain|Btt travesía",
    "image": "https://contents.mediadecathlon.com/p2839092/k$c689f75b535976bb72400f8fe1f3f241/picture.jpg?f=300x300",
    "url": "https://www.decathlon.es/es/p/culotte-interior-mtb-all-mountain-enduro-feel-proteccion-d3o/359920/c382m8927322",
    "affiliate_url": "https://afiliacion.decathlon.es/tracking/clk?fid=107&pca=8927322|Culotte Interior MTB All Mountain Enduro Feel Protección D3O®|&act=21712&gel=0&pub=42111&org=2615&url=https://www.decathlon.es/es/p/culotte-interior-mtb-all-mountain-enduro-feel-proteccion-d3o/359920/c382m8927322",
    "source": "decathlon",
    "source_label": "Decathlon",
    "price": 54.99,
    "old_price": "",
    "discount_pct": 0,
    "recomendacion": 43,
    "detail_enabled": false,
    "sku": "8927322"
  }
]